odoo/addons/shopfloor_dangerous_goods/README.rst
odoo/addons/shopfloor_dangerous_goods/__init__.py
odoo/addons/shopfloor_dangerous_goods/__manifest__.py
odoo/addons/shopfloor_dangerous_goods/actions/__init__.py
odoo/addons/shopfloor_dangerous_goods/actions/data.py
odoo/addons/shopfloor_dangerous_goods/actions/schema.py
odoo/addons/shopfloor_dangerous_goods/i18n/shopfloor_dangerous_goods.pot
odoo/addons/shopfloor_dangerous_goods/readme/CONTRIBUTORS.rst
odoo/addons/shopfloor_dangerous_goods/readme/DESCRIPTION.rst
odoo/addons/shopfloor_dangerous_goods/static/description/icon.png
odoo/addons/shopfloor_dangerous_goods/static/description/index.html
odoo/addons/shopfloor_dangerous_goods/tests/__init__.py
odoo/addons/shopfloor_dangerous_goods/tests/test_actions_data.py
odoo14_addon_shopfloor_dangerous_goods-14.0.1.1.0.dist-info/METADATA
odoo14_addon_shopfloor_dangerous_goods-14.0.1.1.0.dist-info/WHEEL
odoo14_addon_shopfloor_dangerous_goods-14.0.1.1.0.dist-info/top_level.txt
odoo14_addon_shopfloor_dangerous_goods-14.0.1.1.0.dist-info/RECORD
